prismatic-0.4.dist-info/metadata.json
prismatic-0.4.dist-info/DESCRIPTION.rst
prismatic-0.4.dist-info/RECORD
prismatic-0.4.dist-info/top_level.txt
prismatic-0.4.dist-info/WHEEL
prismatic-0.4.dist-info/METADATA
prismatic/serialization_test.py
prismatic/serialization.py
prismatic/__init__.py
