Metadata-Version: 2.0
Name: prismatic
Version: 0.4
Summary: Serialization between JSON dicts and data objects designed for REST APIs
Home-page: https://github.com/adambyrtek/prismatic
Author: Adam Byrtek
Author-email: adambyrtek@gmail.com
License: MIT
Keywords: json,orm,serialization,api,rest
Platform: UNKNOWN
Requires-Dist: isodate
